Metadata-Version: 2.1
Name: graffito
Version: 0.0.1
Summary: A function-tagging library using decorators as tags.
License-File: LICENSE
